btpytools/__init__.py
btpytools/brainreg_bt.py
btpytools/btrfs.py
btpytools/compressRawData.py
btpytools/recipe.py
btpytools/summariseAcquisitions.py
btpytools/tools.py
btpytools/transferToServer.py
btpytools/__pycache__/.gitignore
btpytools-0.1.37.dist-info/LICENSE
btpytools-0.1.37.dist-info/METADATA
btpytools-0.1.37.dist-info/WHEEL
btpytools-0.1.37.dist-info/entry_points.txt
btpytools-0.1.37.dist-info/top_level.txt
btpytools-0.1.37.dist-info/RECORD
