Metadata-Version: 2.1
Name: btpytools
Version: 0.1.37
Summary: Helper functions for BakingTray and StitchIt
Author: Rob Campbell
License: GPL-3.0-or-later
Project-URL: repository, https://github.com/SWC-Advanced-Microscopy/btpytools
Keywords: anatomy,image analysis,data handling
Classifier: Natural Language :: English
Classifier: Topic :: Scientific/Engineering :: Image Processing
Classifier: License :: Free for non-commercial use
Classifier: Programming Language :: Python :: 3.9
Classifier: Programming Language :: Python :: 3.10
Classifier: Intended Audience :: Developers
Classifier: Intended Audience :: Science/Research
Requires-Python: >=3.9.0
License-File: LICENSE
Requires-Dist: pyyaml
Requires-Dist: types-PyYAML
Requires-Dist: termcolor
Provides-Extra: dev
Requires-Dist: brainreg ; extra == 'dev'
Requires-Dist: ipython ; extra == 'dev'
Requires-Dist: mypy ; extra == 'dev'
Requires-Dist: pytest ; extra == 'dev'
Requires-Dist: setuptools-scm ; extra == 'dev'
Requires-Dist: black ; extra == 'dev'
Requires-Dist: flake8 ; extra == 'dev'
Requires-Dist: pre-commit ; extra == 'dev'
Provides-Extra: register
Requires-Dist: brainreg ; extra == 'register'
